flowmachine/__init__.py
flowmachine/_version.py
flowmachine/utils.py
flowmachine/versions.py
flowmachine/core/__init__.py
flowmachine/core/cache.py
flowmachine/core/connection.py
flowmachine/core/context.py
flowmachine/core/custom_query.py
flowmachine/core/date_range.py
flowmachine/core/dependency_graph.py
flowmachine/core/dummy_query.py
flowmachine/core/geotable.py
flowmachine/core/grid.py
flowmachine/core/hour_slice.py
flowmachine/core/init.py
flowmachine/core/join.py
flowmachine/core/join_to_location.py
flowmachine/core/logging.py
flowmachine/core/query.py
flowmachine/core/query_info_lookup.py
flowmachine/core/query_state.py
flowmachine/core/query_stub.py
flowmachine/core/random.py
flowmachine/core/spatial_unit.py
flowmachine/core/sqlalchemy_table_definitions.py
flowmachine/core/sqlalchemy_utils.py
flowmachine/core/statistic_types.py
flowmachine/core/subscriber_subsetter.py
flowmachine/core/subset.py
flowmachine/core/table.py
flowmachine/core/union.py
flowmachine/core/union_with_fixed_values.py
flowmachine/core/errors/__init__.py
flowmachine/core/errors/flowmachine_errors.py
flowmachine/core/mixins/__init__.py
flowmachine/core/mixins/exposed_datetime_mixin.py
flowmachine/core/mixins/geodata_mixin.py
flowmachine/core/mixins/graph_mixin.py
flowmachine/core/server/__init__.py
flowmachine/core/server/action_handlers.py
flowmachine/core/server/action_request_schema.py
flowmachine/core/server/cache_cleanup.py
flowmachine/core/server/exceptions.py
flowmachine/core/server/server.py
flowmachine/core/server/server_config.py
flowmachine/core/server/utils.py
flowmachine/core/server/zmq_helpers.py
flowmachine/core/server/query_schemas/__init__.py
flowmachine/core/server/query_schemas/active_at_reference_location_counts.py
flowmachine/core/server/query_schemas/aggregate_network_objects.py
flowmachine/core/server/query_schemas/aggregation_unit.py
flowmachine/core/server/query_schemas/base_exposed_query.py
flowmachine/core/server/query_schemas/base_query_with_sampling.py
flowmachine-1.34.0.dist-info/METADATA
flowmachine-1.34.0.dist-info/WHEEL
flowmachine-1.34.0.dist-info/entry_points.txt
flowmachine-1.34.0.dist-info/top_level.txt
flowmachine-1.34.0.dist-info/RECORD
